{
  "classname": null,
  "name": null,
  "animation": {
    "classname": null,
    "name": "AnimationManager",
    "actionlist": []
  },
  "dataScale": 1,
  "designHeight": 750,
  "designWidth": 1124,
  "textures": [],
  "version": "1.2.0.1",
  "widgetTree": {
    "classname": "Panel",
    "name": null,
    "children": [
      {
        "classname": "Panel",
        "name": null,
        "children": [
          {
            "classname": "ImageView",
            "name": null,
            "children": [],
            "options": {
              "__type": "ComGUIImageViewSurrogate:#EditorCommon.JsonModel.Component.GUI",
              "classname": "ImageView",
              "name": "general_up",
              "ZOrder": 0,
              "actiontag": 61462,
              "anchorPointX": 0.5,
              "anchorPointY": 0.5,
              "classType": null,
              "colorB": 255,
              "colorG": 255,
              "colorR": 255,
              "flipX": true,
              "flipY": false,
              "height": 233,
              "ignoreSize": true,
              "layoutParameter": null,
              "opacity": 255,
              "positionPercentX": 0,
              "positionPercentY": 0,
              "positionType": 0,
              "rotation": 0,
              "scaleX": 1,
              "scaleY": 1,
              "sizePercentX": 0,
              "sizePercentY": 0,
              "sizeType": 0,
              "tag": 919,
              "touchAble": false,
              "useMergedTexture": false,
              "visible": true,
              "width": 424,
              "x": -305,
              "y": 155,
              "capInsetsHeight": 0,
              "capInsetsWidth": 0,
              "capInsetsX": 0,
              "capInsetsY": 0,
              "fileName": null,
              "fileNameData": {
                "path": "image/general_one.png",
                "plistFile": null,
                "resourceType": 0
              },
              "scale9Enable": false,
              "scale9Height": 233,
              "scale9Width": 424
            }
          },
          {
            "classname": "ImageView",
            "name": null,
            "children": [],
            "options": {
              "__type": "ComGUIImageViewSurrogate:#EditorCommon.JsonModel.Component.GUI",
              "classname": "ImageView",
              "name": "general_down",
              "ZOrder": 0,
              "actiontag": 61463,
              "anchorPointX": 0.5,
              "anchorPointY": 0.5,
              "classType": null,
              "colorB": 255,
              "colorG": 255,
              "colorR": 255,
              "flipX": false,
              "flipY": true,
              "height": 233,
              "ignoreSize": true,
              "layoutParameter": null,
              "opacity": 255,
              "positionPercentX": 0,
              "positionPercentY": 0,
              "positionType": 0,
              "rotation": 0,
              "scaleX": 1,
              "scaleY": 1,
              "sizePercentX": 0,
              "sizePercentY": 0,
              "sizeType": 0,
              "tag": 919,
              "touchAble": false,
              "useMergedTexture": false,
              "visible": true,
              "width": 424,
              "x": 283,
              "y": -231,
              "capInsetsHeight": 0,
              "capInsetsWidth": 0,
              "capInsetsX": 0,
              "capInsetsY": 0,
              "fileName": null,
              "fileNameData": {
                "path": "image/general_one.png",
                "plistFile": null,
                "resourceType": 0
              },
              "scale9Enable": false,
              "scale9Height": 233,
              "scale9Width": 424
            }
          },
          {
            "classname": "ImageView",
            "name": null,
            "children": [
              {
                "classname": "ImageView",
                "name": null,
                "children": [],
                "options": {
                  "__type": "ComGUIImageViewSurrogate:#EditorCommon.JsonModel.Component.GUI",
                  "classname": "ImageView",
                  "name": "title",
                  "ZOrder": 1,
                  "actiontag": 61450,
                  "anchorPointX": 0.5,
                  "anchorPointY": 0.5,
                  "classType": null,
                  "colorB": 255,
                  "colorG": 255,
                  "colorR": 255,
                  "flipX": false,
                  "flipY": false,
                  "height": 44,
                  "ignoreSize": true,
                  "layoutParameter": null,
                  "opacity": 255,
                  "positionPercentX": 0,
                  "positionPercentY": 0,
                  "positionType": 0,
                  "rotation": 0,
                  "scaleX": 1,
                  "scaleY": 1,
                  "sizePercentX": 0.3018868,
                  "sizePercentY": 1.17647064,
                  "sizeType": 0,
                  "tag": 907,
                  "touchAble": false,
                  "useMergedTexture": false,
                  "visible": true,
                  "width": 126,
                  "x": 0,
                  "y": 0,
                  "capInsetsHeight": 0,
                  "capInsetsWidth": 0,
                  "capInsetsX": 0,
                  "capInsetsY": 0,
                  "fileName": null,
                  "fileNameData": {
                    "path": "typeface/ranking_list.png",
                    "plistFile": null,
                    "resourceType": 0
                  },
                  "scale9Enable": false,
                  "scale9Height": 44,
                  "scale9Width": 126
                }
              }
            ],
            "options": {
              "__type": "ComGUIImageViewSurrogate:#EditorCommon.JsonModel.Component.GUI",
              "classname": "ImageView",
              "name": "map_title",
              "ZOrder": 10,
              "actiontag": 61449,
              "anchorPointX": 0.5,
              "anchorPointY": 0.5,
              "classType": null,
              "colorB": 255,
              "colorG": 255,
              "colorR": 255,
              "flipX": false,
              "flipY": false,
              "height": 68,
              "ignoreSize": true,
              "layoutParameter": null,
              "opacity": 255,
              "positionPercentX": 0,
              "positionPercentY": 0,
              "positionType": 0,
              "rotation": 0,
              "scaleX": 1,
              "scaleY": 1,
              "sizePercentX": 0,
              "sizePercentY": 0,
              "sizeType": 0,
              "tag": 906,
              "touchAble": false,
              "useMergedTexture": false,
              "visible": true,
              "width": 265,
              "x": -10,
              "y": 255,
              "capInsetsHeight": 0,
              "capInsetsWidth": 0,
              "capInsetsX": 0,
              "capInsetsY": 0,
              "fileName": null,
              "fileNameData": {
                "path": "image/map_title.png",
                "plistFile": null,
                "resourceType": 0
              },
              "scale9Enable": false,
              "scale9Height": 68,
              "scale9Width": 265
            }
          },
          {
            "classname": "ListView",
            "name": null,
            "children": [
              {
                "classname": "ImageView",
                "name": null,
                "children": [
                  {
                    "classname": "ImageView",
                    "name": null,
                    "children": [],
                    "options": {
                      "__type": "ComGUIImageViewSurrogate:#EditorCommon.JsonModel.Component.GUI",
                      "classname": "ImageView",
                      "name": "head_box",
                      "ZOrder": 0,
                      "actiontag": 61456,
                      "anchorPointX": 0.5,
                      "anchorPointY": 0.5,
                      "classType": null,
                      "colorB": 255,
                      "colorG": 255,
                      "colorR": 255,
                      "flipX": false,
                      "flipY": false,
                      "height": 116,
                      "ignoreSize": true,
                      "layoutParameter": null,
                      "opacity": 255,
                      "positionPercentX": -0.280397028,
                      "positionPercentY": -0.00649350649,
                      "positionType": 0,
                      "rotation": 0,
                      "scaleX": 1,
                      "scaleY": 1,
                      "sizePercentX": 0.0992555842,
                      "sizePercentY": 0.5194805,
                      "sizeType": 0,
                      "tag": 913,
                      "touchAble": false,
                      "useMergedTexture": false,
                      "visible": true,
                      "width": 113,
                      "x": -226,
                      "y": -1,
                      "capInsetsHeight": 0,
                      "capInsetsWidth": 0,
                      "capInsetsX": 0,
                      "capInsetsY": 0,
                      "fileName": null,
                      "fileNameData": {
                        "path": "image/head_blue.png",
                        "plistFile": null,
                        "resourceType": 0
                      },
                      "scale9Enable": false,
                      "scale9Height": 116,
                      "scale9Width": 113
                    }
                  },
                  {
                    "classname": "ImageView",
                    "name": null,
                    "children": [],
                    "options": {
                      "__type": "ComGUIImageViewSurrogate:#EditorCommon.JsonModel.Component.GUI",
                      "classname": "ImageView",
                      "name": "img_lv",
                      "ZOrder": 1,
                      "actiontag": 61458,
                      "anchorPointX": 0.5,
                      "anchorPointY": 0.5,
                      "classType": null,
                      "colorB": 255,
                      "colorG": 255,
                      "colorR": 255,
                      "flipX": false,
                      "flipY": false,
                      "height": 29,
                      "ignoreSize": true,
                      "layoutParameter": null,
                      "opacity": 255,
                      "positionPercentX": 0.0446650125,
                      "positionPercentY": 0,
                      "positionType": 0,
                      "rotation": 0,
                      "scaleX": 1,
                      "scaleY": 1,
                      "sizePercentX": 0.0992555842,
                      "sizePercentY": 0.5194805,
                      "sizeType": 0,
                      "tag": 915,
                      "touchAble": false,
                      "useMergedTexture": false,
                      "visible": true,
                      "width": 54,
                      "x": 36,
                      "y": 0,
                      "capInsetsHeight": 0,
                      "capInsetsWidth": 0,
                      "capInsetsX": 0,
                      "capInsetsY": 0,
                      "fileName": null,
                      "fileNameData": {
                        "path": "image/level.png",
                        "plistFile": null,
                        "resourceType": 0
                      },
                      "scale9Enable": false,
                      "scale9Height": 29,
                      "scale9Width": 54
                    }
                  },
                  {
                    "classname": "ImageView",
                    "name": null,
                    "children": [],
                    "options": {
                      "__type": "ComGUIImageViewSurrogate:#EditorCommon.JsonModel.Component.GUI",
                      "classname": "ImageView",
                      "name": "star",
                      "ZOrder": 2,
                      "actiontag": 61460,
                      "anchorPointX": 0.5,
                      "anchorPointY": 0.5,
                      "classType": null,
                      "colorB": 255,
                      "colorG": 255,
                      "colorR": 255,
                      "flipX": false,
                      "flipY": false,
                      "height": 74,
                      "ignoreSize": true,
                      "layoutParameter": null,
                      "opacity": 255,
                      "positionPercentX": 0.222084373,
                      "positionPercentY": 0.0259740259,
                      "positionType": 0,
                      "rotation": 0,
                      "scaleX": 0.799999952,
                      "scaleY": 0.799999952,
                      "sizePercentX": 0.0992555842,
                      "sizePercentY": 0.5194805,
                      "sizeType": 0,
                      "tag": 917,
                      "touchAble": false,
                      "useMergedTexture": false,
                      "visible": true,
                      "width": 69,
                      "x": 179,
                      "y": 4,
                      "capInsetsHeight": 0,
                      "capInsetsWidth": 0,
                      "capInsetsX": 0,
                      "capInsetsY": 0,
                      "fileName": null,
                      "fileNameData": {
                        "path": "image/star.png",
                        "plistFile": null,
                        "resourceType": 0
                      },
                      "scale9Enable": false,
                      "scale9Height": 74,
                      "scale9Width": 69
                    }
                  },
                  {
                    "classname": "ImageView",
                    "name": null,
                    "children": [],
                    "options": {
                      "__type": "ComGUIImageViewSurrogate:#EditorCommon.JsonModel.Component.GUI",
                      "classname": "ImageView",
                      "name": "rank_cnt",
                      "ZOrder": 5,
                      "actiontag": 61455,
                      "anchorPointX": 0.5,
                      "anchorPointY": 0.5,
                      "classType": null,
                      "colorB": 255,
                      "colorG": 255,
                      "colorR": 255,
                      "flipX": false,
                      "flipY": false,
                      "height": 65,
                      "ignoreSize": true,
                      "layoutParameter": null,
                      "opacity": 255,
                      "positionPercentX": -0.4280397,
                      "positionPercentY": 0.019480519,
                      "positionType": 0,
                      "rotation": 0,
                      "scaleX": 1,
                      "scaleY": 1,
                      "sizePercentX": 0.0992555842,
                      "sizePercentY": 0.5194805,
                      "sizeType": 0,
                      "tag": 912,
                      "touchAble": false,
                      "useMergedTexture": false,
                      "visible": true,
                      "width": 50,
                      "x": -345,
                      "y": 3,
                      "capInsetsHeight": 0,
                      "capInsetsWidth": 0,
                      "capInsetsX": 0,
                      "capInsetsY": 0,
                      "fileName": null,
                      "fileNameData": {
                        "path": "ranking_list/1.png",
                        "plistFile": null,
                        "resourceType": 0
                      },
                      "scale9Enable": false,
                      "scale9Height": 65,
                      "scale9Width": 50
                    }
                  },
                  {
                    "classname": "Label",
                    "name": null,
                    "children": [],
                    "options": {
                      "__type": "ComGUILabelSurrogate:#EditorCommon.JsonModel.Component.GUI",
                      "classname": "Label",
                      "name": "name",
                      "ZOrder": 6,
                      "actiontag": 61457,
                      "anchorPointX": 0,
                      "anchorPointY": 0.5,
                      "classType": null,
                      "colorB": 255,
                      "colorG": 255,
                      "colorR": 255,
                      "flipX": false,
                      "flipY": false,
                      "height": 27,
                      "ignoreSize": true,
                      "layoutParameter": null,
                      "opacity": 255,
                      "positionPercentX": -0.204714641,
                      "positionPercentY": 0.012987013,
                      "positionType": 0,
                      "rotation": 0,
                      "scaleX": 1,
                      "scaleY": 1,
                      "sizePercentX": 0.117866,
                      "sizePercentY": 0.175324678,
                      "sizeType": 0,
                      "tag": 914,
                      "touchAble": false,
                      "useMergedTexture": false,
                      "visible": true,
                      "width": 95,
                      "x": -165,
                      "y": 2,
                      "areaHeight": 0,
                      "areaWidth": 0,
                      "fontFile": null,
                      "fontName": "微软雅黑",
                      "fontSize": 22,
                      "hAlignment": 0,
                      "text": "充钱就是吊",
                      "touchScaleEnable": false,
                      "vAlignment": 0
                    }
                  },
                  {
                    "classname": "LabelAtlas",
                    "name": null,
                    "children": [],
                    "options": {
                      "__type": "ComGUILabelAtlasSurrogate:#EditorCommon.JsonModel.Component.GUI",
                      "classname": "LabelAtlas",
                      "name": "atlas_lv",
                      "ZOrder": 10,
                      "actiontag": 61459,
                      "anchorPointX": 0,
                      "anchorPointY": 0.5,
                      "classType": null,
                      "colorB": 255,
                      "colorG": 255,
                      "colorR": 255,
                      "flipX": false,
                      "flipY": false,
                      "height": 32,
                      "ignoreSize": true,
                      "layoutParameter": null,
                      "opacity": 255,
                      "positionPercentX": 0.08064516,
                      "positionPercentY": 0,
                      "positionType": 0,
                      "rotation": 0,
                      "scaleX": 1,
                      "scaleY": 1,
                      "sizePercentX": 0.297766745,
                      "sizePercentY": 0.207792208,
                      "sizeType": 0,
                      "tag": 916,
                      "touchAble": false,
                      "useMergedTexture": false,
                      "visible": true,
                      "width": 24,
                      "x": 65,
                      "y": 0,
                      "charMapFile": null,
                      "charMapFileData": {
                        "path": "GUI/labelatlasimg2.png",
                        "plistFile": null,
                        "resourceType": 0
                      },
                      "itemHeight": 32,
                      "itemWidth": 24,
                      "startCharMap": "0",
                      "stringValue": "8"
                    }
                  },
                  {
                    "classname": "LabelAtlas",
                    "name": null,
                    "children": [],
                    "options": {
                      "__type": "ComGUILabelAtlasSurrogate:#EditorCommon.JsonModel.Component.GUI",
                      "classname": "LabelAtlas",
                      "name": "atlas_star",
                      "ZOrder": 10,
                      "actiontag": 61461,
                      "anchorPointX": 0,
                      "anchorPointY": 0.5,
                      "classType": null,
                      "colorB": 255,
                      "colorG": 255,
                      "colorR": 255,
                      "flipX": false,
                      "flipY": false,
                      "height": 32,
                      "ignoreSize": true,
                      "layoutParameter": null,
                      "opacity": 255,
                      "positionPercentX": 0.2593052,
                      "positionPercentY": 0,
                      "positionType": 0,
                      "rotation": 0,
                      "scaleX": 1,
                      "scaleY": 1,
                      "sizePercentX": 0.297766745,
                      "sizePercentY": 0.207792208,
                      "sizeType": 0,
                      "tag": 918,
                      "touchAble": false,
                      "useMergedTexture": false,
                      "visible": true,
                      "width": 48,
                      "x": 209,
                      "y": 0,
                      "charMapFile": null,
                      "charMapFileData": {
                        "path": "GUI/labelatlasimg.png",
                        "plistFile": null,
                        "resourceType": 0
                      },
                      "itemHeight": 32,
                      "itemWidth": 24,
                      "startCharMap": "0",
                      "stringValue": "50"
                    }
                  }
                ],
                "options": {
                  "__type": "ComGUIImageViewSurrogate:#EditorCommon.JsonModel.Component.GUI",
                  "classname": "ImageView",
                  "name": "floor",
                  "ZOrder": 0,
                  "actiontag": 61452,
                  "anchorPointX": 0.5,
                  "anchorPointY": 0.5,
                  "classType": null,
                  "colorB": 255,
                  "colorG": 255,
                  "colorR": 255,
                  "flipX": false,
                  "flipY": false,
                  "height": 154,
                  "ignoreSize": true,
                  "layoutParameter": null,
                  "opacity": 255,
                  "positionPercentX": 0.492665023,
                  "positionPercentY": 0.8431772,
                  "positionType": 0,
                  "rotation": 0,
                  "scaleX": 1,
                  "scaleY": 1,
                  "sizePercentX": 0.09779951,
                  "sizePercentY": 0.162932783,
                  "sizeType": 0,
                  "tag": 909,
                  "touchAble": false,
                  "useMergedTexture": false,
                  "visible": true,
                  "width": 806,
                  "x": 403,
                  "y": 414,
                  "capInsetsHeight": 0,
                  "capInsetsWidth": 0,
                  "capInsetsX": 0,
                  "capInsetsY": 0,
                  "fileName": null,
                  "fileNameData": {
                    "path": "ranking_list/floor.png",
                    "plistFile": null,
                    "resourceType": 0
                  },
                  "scale9Enable": false,
                  "scale9Height": 154,
                  "scale9Width": 806
                }
              }
            ],
            "options": {
              "__type": "ComGUIListViewSurrogate:#EditorCommon.JsonModel.Component.GUI",
              "classname": "ListView",
              "name": "list_view",
              "ZOrder": 5,
              "actiontag": 61451,
              "anchorPointX": 0,
              "anchorPointY": 0,
              "classType": null,
              "colorB": 255,
              "colorG": 255,
              "colorR": 255,
              "flipX": false,
              "flipY": false,
              "height": 491,
              "ignoreSize": false,
              "layoutParameter": null,
              "opacity": 255,
              "positionPercentX": 0,
              "positionPercentY": 0,
              "positionType": 0,
              "rotation": 0,
              "scaleX": 1,
              "scaleY": 1,
              "sizePercentX": 0,
              "sizePercentY": 0,
              "sizeType": 0,
              "tag": 908,
              "touchAble": true,
              "useMergedTexture": false,
              "visible": true,
              "width": 818,
              "x": -446,
              "y": -287,
              "backGroundImage": null,
              "backGroundImageData": null,
              "backGroundScale9Enable": false,
              "bgColorB": 255,
              "bgColorG": 150,
              "bgColorOpacity": 0,
              "bgColorR": 150,
              "bgEndColorB": 255,
              "bgEndColorG": 150,
              "bgEndColorR": 150,
              "bgStartColorB": 255,
              "bgStartColorG": 255,
              "bgStartColorR": 255,
              "bounceEnable": false,
              "capInsetsHeight": 0,
              "capInsetsWidth": 0,
              "capInsetsX": 0,
              "capInsetsY": 0,
              "clipAble": true,
              "colorType": 0,
              "direction": 1,
              "gravity": 0,
              "innerHeight": 491,
              "innerWidth": 818,
              "itemMargin": 13,
              "vectorX": 0,
              "vectorY": -0.5
            }
          }
        ],
        "options": {
          "__type": "ComGUIPanelSurrogate:#EditorCommon.JsonModel.Component.GUI",
          "classname": "Panel",
          "name": "center",
          "ZOrder": 13,
          "actiontag": 62463,
          "anchorPointX": 0,
          "anchorPointY": 0,
          "classType": null,
          "colorB": 255,
          "colorG": 255,
          "colorR": 255,
          "flipX": false,
          "flipY": false,
          "height": 0,
          "ignoreSize": false,
          "layoutParameter": null,
          "opacity": 255,
          "positionPercentX": 0.5,
          "positionPercentY": 0.5,
          "positionType": 1,
          "rotation": 0,
          "scaleX": 1,
          "scaleY": 1,
          "sizePercentX": 0,
          "sizePercentY": 0,
          "sizeType": 0,
          "tag": 780,
          "touchAble": false,
          "useMergedTexture": false,
          "visible": true,
          "width": 0,
          "x": 562,
          "y": 375,
          "backGroundImage": null,
          "backGroundImageData": null,
          "backGroundScale9Enable": false,
          "bgColorB": 255,
          "bgColorG": 200,
          "bgColorOpacity": 0,
          "bgColorR": 150,
          "bgEndColorB": 255,
          "bgEndColorG": 200,
          "bgEndColorR": 150,
          "bgStartColorB": 255,
          "bgStartColorG": 255,
          "bgStartColorR": 255,
          "capInsetsHeight": 0,
          "capInsetsWidth": 0,
          "capInsetsX": 0,
          "capInsetsY": 0,
          "clipAble": false,
          "colorType": 0,
          "layoutType": 0,
          "vectorX": 0,
          "vectorY": -0.5
        }
      }
    ],
    "options": {
      "__type": "ComGUIPanelSurrogate:#EditorCommon.JsonModel.Component.GUI",
      "classname": "Panel",
      "name": "panel",
      "ZOrder": 0,
      "actiontag": -1,
      "anchorPointX": 0,
      "anchorPointY": 0,
      "classType": null,
      "colorB": 255,
      "colorG": 255,
      "colorR": 255,
      "flipX": false,
      "flipY": false,
      "height": 750,
      "ignoreSize": false,
      "layoutParameter": null,
      "opacity": 255,
      "positionPercentX": 0,
      "positionPercentY": 0,
      "positionType": 0,
      "rotation": 0,
      "scaleX": 1,
      "scaleY": 1,
      "sizePercentX": 1,
      "sizePercentY": 1,
      "sizeType": 0,
      "tag": 862,
      "touchAble": true,
      "useMergedTexture": false,
      "visible": true,
      "width": 1124,
      "x": 0,
      "y": 0,
      "backGroundImage": null,
      "backGroundImageData": {
        "path": "image/general_background_1.jpg",
        "plistFile": null,
        "resourceType": 0
      },
      "backGroundScale9Enable": false,
      "bgColorB": 255,
      "bgColorG": 200,
      "bgColorOpacity": 0,
      "bgColorR": 150,
      "bgEndColorB": 255,
      "bgEndColorG": 200,
      "bgEndColorR": 150,
      "bgStartColorB": 255,
      "bgStartColorG": 255,
      "bgStartColorR": 255,
      "capInsetsHeight": 0,
      "capInsetsWidth": 0,
      "capInsetsX": 0,
      "capInsetsY": 0,
      "clipAble": false,
      "colorType": 1,
      "layoutType": 0,
      "vectorX": 0,
      "vectorY": -0.5
    }
  }
}