{
  "classname": null,
  "name": null,
  "animation": {
    "classname": null,
    "name": "AnimationManager",
    "actionlist": []
  },
  "dataScale": 1,
  "designHeight": 750,
  "designWidth": 1124,
  "textures": [],
  "version": "1.2.0.1",
  "widgetTree": {
    "classname": "Panel",
    "name": null,
    "children": [
      {
        "classname": "ImageView",
        "name": null,
        "children": [
          {
            "classname": "Button",
            "name": null,
            "children": [],
            "options": {
              "__type": "ComGUIButtonSurrogate:#EditorCommon.JsonModel.Component.GUI",
              "classname": "Button",
              "name": "btn_close",
              "ZOrder": 10,
              "actiontag": 40075,
              "anchorPointX": 0.5,
              "anchorPointY": 0.5,
              "classType": null,
              "colorB": 255,
              "colorG": 255,
              "colorR": 255,
              "flipX": false,
              "flipY": false,
              "height": 49,
              "ignoreSize": true,
              "layoutParameter": null,
              "opacity": 255,
              "positionPercentX": 0.415478617,
              "positionPercentY": 0.424242437,
              "positionType": 0,
              "rotation": 0,
              "scaleX": 1,
              "scaleY": 1,
              "sizePercentX": 0.209775969,
              "sizePercentY": 0.08080808,
              "sizeType": 0,
              "tag": 946,
              "touchAble": true,
              "useMergedTexture": false,
              "visible": true,
              "width": 60,
              "x": 204,
              "y": 210,
              "capInsetsHeight": 0,
              "capInsetsWidth": 0,
              "capInsetsX": 0,
              "capInsetsY": 0,
              "disabled": null,
              "disabledData": {
                "path": "image/general_closure.png",
                "plistFile": null,
                "resourceType": 0
              },
              "fontName": "微软雅黑",
              "fontSize": 14,
              "fontType": 0,
              "normal": null,
              "normalData": {
                "path": "image/general_closure.png",
                "plistFile": null,
                "resourceType": 0
              },
              "pressed": null,
              "pressedData": {
                "path": "image/general_closure.png",
                "plistFile": null,
                "resourceType": 0
              },
              "scale9Enable": false,
              "scale9Height": 49,
              "scale9Width": 60,
              "text": "",
              "textColorB": 255,
              "textColorG": 255,
              "textColorR": 255
            }
          },
          {
            "classname": "ImageView",
            "name": null,
            "children": [],
            "options": {
              "__type": "ComGUIImageViewSurrogate:#EditorCommon.JsonModel.Component.GUI",
              "classname": "ImageView",
              "name": "title",
              "ZOrder": 1,
              "actiontag": 40054,
              "anchorPointX": 0.5,
              "anchorPointY": 0.5,
              "classType": null,
              "colorB": 255,
              "colorG": 255,
              "colorR": 255,
              "flipX": false,
              "flipY": false,
              "height": 34,
              "ignoreSize": true,
              "layoutParameter": null,
              "opacity": 255,
              "positionPercentX": 0.00203666,
              "positionPercentY": 0.442424238,
              "positionType": 0,
              "rotation": 0,
              "scaleX": 1,
              "scaleY": 1,
              "sizePercentX": 0.162932783,
              "sizePercentY": 0.161616161,
              "sizeType": 0,
              "tag": 925,
              "touchAble": false,
              "useMergedTexture": false,
              "visible": true,
              "width": 65,
              "x": 1,
              "y": 219,
              "capInsetsHeight": 0,
              "capInsetsWidth": 0,
              "capInsetsX": 0,
              "capInsetsY": 0,
              "fileName": null,
              "fileNameData": {
                "path": "typeface/sweep_title.png",
                "plistFile": null,
                "resourceType": 0
              },
              "scale9Enable": false,
              "scale9Height": 34,
              "scale9Width": 65
            }
          },
          {
            "classname": "ImageView",
            "name": null,
            "children": [],
            "options": {
              "__type": "ComGUIImageViewSurrogate:#EditorCommon.JsonModel.Component.GUI",
              "classname": "ImageView",
              "name": "item_goods",
              "ZOrder": 1,
              "actiontag": 40074,
              "anchorPointX": 0.5,
              "anchorPointY": 0.5,
              "classType": null,
              "colorB": 255,
              "colorG": 255,
              "colorR": 255,
              "flipX": false,
              "flipY": false,
              "height": 78,
              "ignoreSize": true,
              "layoutParameter": null,
              "opacity": 255,
              "positionPercentX": -0.321792275,
              "positionPercentY": 0.145454541,
              "positionType": 0,
              "rotation": 0,
              "scaleX": 1,
              "scaleY": 1,
              "sizePercentX": 0.162932783,
              "sizePercentY": 0.161616161,
              "sizeType": 0,
              "tag": 941,
              "touchAble": false,
              "useMergedTexture": false,
              "visible": true,
              "width": 78,
              "x": -158,
              "y": 72,
              "capInsetsHeight": 0,
              "capInsetsWidth": 0,
              "capInsetsX": 0,
              "capInsetsY": 0,
              "fileName": null,
              "fileNameData": {
                "path": "image/green_box.png",
                "plistFile": null,
                "resourceType": 0
              },
              "scale9Enable": false,
              "scale9Height": 78,
              "scale9Width": 78
            }
          },
          {
            "classname": "ListView",
            "name": null,
            "children": [
              {
                "classname": "Panel",
                "name": null,
                "children": [
                  {
                    "classname": "ImageView",
                    "name": null,
                    "children": [],
                    "options": {
                      "__type": "ComGUIImageViewSurrogate:#EditorCommon.JsonModel.Component.GUI",
                      "classname": "ImageView",
                      "name": "title_bg",
                      "ZOrder": 0,
                      "actiontag": 40057,
                      "anchorPointX": 0.5,
                      "anchorPointY": 0.5,
                      "classType": null,
                      "colorB": 255,
                      "colorG": 255,
                      "colorR": 255,
                      "flipX": false,
                      "flipY": false,
                      "height": 27,
                      "ignoreSize": true,
                      "layoutParameter": null,
                      "opacity": 255,
                      "positionPercentX": 0.533333361,
                      "positionPercentY": 0.8717949,
                      "positionType": 0,
                      "rotation": 0,
                      "scaleX": 1,
                      "scaleY": 1,
                      "sizePercentX": 0.1904762,
                      "sizePercentY": 0.512820542,
                      "sizeType": 0,
                      "tag": 928,
                      "touchAble": false,
                      "useMergedTexture": false,
                      "visible": true,
                      "width": 397,
                      "x": 224,
                      "y": 136,
                      "capInsetsHeight": 0,
                      "capInsetsWidth": 0,
                      "capInsetsX": 0,
                      "capInsetsY": 0,
                      "fileName": null,
                      "fileNameData": {
                        "path": "checkpoint/level_introduction/sweep/floor_3.png",
                        "plistFile": null,
                        "resourceType": 0
                      },
                      "scale9Enable": false,
                      "scale9Height": 27,
                      "scale9Width": 397
                    }
                  },
                  {
                    "classname": "ImageView",
                    "name": null,
                    "children": [],
                    "options": {
                      "__type": "ComGUIImageViewSurrogate:#EditorCommon.JsonModel.Component.GUI",
                      "classname": "ImageView",
                      "name": "image_exp",
                      "ZOrder": 0,
                      "actiontag": 40068,
                      "anchorPointX": 0.5,
                      "anchorPointY": 0.5,
                      "classType": null,
                      "colorB": 255,
                      "colorG": 255,
                      "colorR": 255,
                      "flipX": false,
                      "flipY": false,
                      "height": 25,
                      "ignoreSize": true,
                      "layoutParameter": null,
                      "opacity": 255,
                      "positionPercentX": 0.142857149,
                      "positionPercentY": 0.6858974,
                      "positionType": 0,
                      "rotation": 0,
                      "scaleX": 1,
                      "scaleY": 1,
                      "sizePercentX": 0.1904762,
                      "sizePercentY": 0.512820542,
                      "sizeType": 0,
                      "tag": 937,
                      "touchAble": false,
                      "useMergedTexture": false,
                      "visible": true,
                      "width": 67,
                      "x": 60,
                      "y": 107,
                      "capInsetsHeight": 0,
                      "capInsetsWidth": 0,
                      "capInsetsX": 0,
                      "capInsetsY": 0,
                      "fileName": null,
                      "fileNameData": {
                        "path": "image/exp_word.png",
                        "plistFile": null,
                        "resourceType": 0
                      },
                      "scale9Enable": false,
                      "scale9Height": 25,
                      "scale9Width": 67
                    }
                  },
                  {
                    "classname": "ImageView",
                    "name": null,
                    "children": [],
                    "options": {
                      "__type": "ComGUIImageViewSurrogate:#EditorCommon.JsonModel.Component.GUI",
                      "classname": "ImageView",
                      "name": "image_gold",
                      "ZOrder": 0,
                      "actiontag": 40066,
                      "anchorPointX": 0.5,
                      "anchorPointY": 0.5,
                      "classType": null,
                      "colorB": 255,
                      "colorG": 255,
                      "colorR": 255,
                      "flipX": false,
                      "flipY": false,
                      "height": 52,
                      "ignoreSize": true,
                      "layoutParameter": null,
                      "opacity": 255,
                      "positionPercentX": 0.788095236,
                      "positionPercentY": 0.6858974,
                      "positionType": 0,
                      "rotation": 0,
                      "scaleX": 0.7,
                      "scaleY": 0.7,
                      "sizePercentX": 0.1904762,
                      "sizePercentY": 0.512820542,
                      "sizeType": 0,
                      "tag": 937,
                      "touchAble": false,
                      "useMergedTexture": false,
                      "visible": true,
                      "width": 52,
                      "x": 331,
                      "y": 107,
                      "capInsetsHeight": 0,
                      "capInsetsWidth": 0,
                      "capInsetsX": 0,
                      "capInsetsY": 0,
                      "fileName": null,
                      "fileNameData": {
                        "path": "image/Gold_iocn.png",
                        "plistFile": null,
                        "resourceType": 0
                      },
                      "scale9Enable": false,
                      "scale9Height": 52,
                      "scale9Width": 52
                    }
                  },
                  {
                    "classname": "Label",
                    "name": null,
                    "children": [],
                    "options": {
                      "__type": "ComGUILabelSurrogate:#EditorCommon.JsonModel.Component.GUI",
                      "classname": "Label",
                      "name": "label_title",
                      "ZOrder": 1,
                      "actiontag": 40058,
                      "anchorPointX": 0.5,
                      "anchorPointY": 0.5,
                      "classType": null,
                      "colorB": 255,
                      "colorG": 255,
                      "colorR": 255,
                      "flipX": false,
                      "flipY": false,
                      "height": 27,
                      "ignoreSize": true,
                      "layoutParameter": null,
                      "opacity": 255,
                      "positionPercentX": 0.5,
                      "positionPercentY": 0.8717949,
                      "positionType": 0,
                      "rotation": 0,
                      "scaleX": 1,
                      "scaleY": 1,
                      "sizePercentX": 0.226190478,
                      "sizePercentY": 0.173076928,
                      "sizeType": 0,
                      "tag": 929,
                      "touchAble": false,
                      "useMergedTexture": false,
                      "visible": true,
                      "width": 95,
                      "x": 210,
                      "y": 136,
                      "areaHeight": 0,
                      "areaWidth": 0,
                      "fontFile": null,
                      "fontName": "微软雅黑",
                      "fontSize": 20,
                      "hAlignment": 0,
                      "text": "第一战",
                      "touchScaleEnable": false,
                      "vAlignment": 0
                    }
                  },
                  {
                    "classname": "Label",
                    "name": null,
                    "children": [],
                    "options": {
                      "__type": "ComGUILabelSurrogate:#EditorCommon.JsonModel.Component.GUI",
                      "classname": "Label",
                      "name": "label_exp",
                      "ZOrder": 10,
                      "actiontag": 40069,
                      "anchorPointX": 0,
                      "anchorPointY": 0.5,
                      "classType": null,
                      "colorB": 255,
                      "colorG": 255,
                      "colorR": 255,
                      "flipX": false,
                      "flipY": false,
                      "height": 27,
                      "ignoreSize": true,
                      "layoutParameter": null,
                      "opacity": 255,
                      "positionPercentX": 0.2452381,
                      "positionPercentY": 0.679487169,
                      "positionType": 0,
                      "rotation": 0,
                      "scaleX": 1,
                      "scaleY": 1,
                      "sizePercentX": 0.226190478,
                      "sizePercentY": 0.173076928,
                      "sizeType": 0,
                      "tag": 938,
                      "touchAble": false,
                      "useMergedTexture": false,
                      "visible": true,
                      "width": 95,
                      "x": 103,
                      "y": 106,
                      "areaHeight": 0,
                      "areaWidth": 0,
                      "fontFile": null,
                      "fontName": "微软雅黑",
                      "fontSize": 20,
                      "hAlignment": 0,
                      "text": "60",
                      "touchScaleEnable": false,
                      "vAlignment": 0
                    }
                  },
                  {
                    "classname": "Label",
                    "name": null,
                    "children": [],
                    "options": {
                      "__type": "ComGUILabelSurrogate:#EditorCommon.JsonModel.Component.GUI",
                      "classname": "Label",
                      "name": "label_gold",
                      "ZOrder": 10,
                      "actiontag": 40067,
                      "anchorPointX": 0,
                      "anchorPointY": 0.5,
                      "classType": null,
                      "colorB": 255,
                      "colorG": 255,
                      "colorR": 255,
                      "flipX": false,
                      "flipY": false,
                      "height": 27,
                      "ignoreSize": true,
                      "layoutParameter": null,
                      "opacity": 255,
                      "positionPercentX": 0.857142866,
                      "positionPercentY": 0.6858974,
                      "positionType": 0,
                      "rotation": 0,
                      "scaleX": 1,
                      "scaleY": 1,
                      "sizePercentX": 0.226190478,
                      "sizePercentY": 0.173076928,
                      "sizeType": 0,
                      "tag": 938,
                      "touchAble": false,
                      "useMergedTexture": false,
                      "visible": true,
                      "width": 95,
                      "x": 360,
                      "y": 107,
                      "areaHeight": 0,
                      "areaWidth": 0,
                      "fontFile": null,
                      "fontName": "微软雅黑",
                      "fontSize": 20,
                      "hAlignment": 0,
                      "text": "60",
                      "touchScaleEnable": false,
                      "vAlignment": 0
                    }
                  },
                  {
                    "classname": "ListView",
                    "name": null,
                    "children": [],
                    "options": {
                      "__type": "ComGUIListViewSurrogate:#EditorCommon.JsonModel.Component.GUI",
                      "classname": "ListView",
                      "name": "listview",
                      "ZOrder": 0,
                      "actiontag": 40056,
                      "anchorPointX": 0,
                      "anchorPointY": 0,
                      "classType": null,
                      "colorB": 255,
                      "colorG": 255,
                      "colorR": 255,
                      "flipX": false,
                      "flipY": false,
                      "height": 82,
                      "ignoreSize": false,
                      "layoutParameter": null,
                      "opacity": 255,
                      "positionPercentX": 0.030952381,
                      "positionPercentY": 0.00641025649,
                      "positionType": 0,
                      "rotation": 0,
                      "scaleX": 1,
                      "scaleY": 1,
                      "sizePercentX": 0.9452381,
                      "sizePercentY": 0.525641,
                      "sizeType": 0,
                      "tag": 927,
                      "touchAble": true,
                      "useMergedTexture": false,
                      "visible": true,
                      "width": 397,
                      "x": 13,
                      "y": 1,
                      "backGroundImage": null,
                      "backGroundImageData": null,
                      "backGroundScale9Enable": false,
                      "bgColorB": 255,
                      "bgColorG": 150,
                      "bgColorOpacity": 100,
                      "bgColorR": 150,
                      "bgEndColorB": 255,
                      "bgEndColorG": 150,
                      "bgEndColorR": 150,
                      "bgStartColorB": 255,
                      "bgStartColorG": 255,
                      "bgStartColorR": 255,
                      "bounceEnable": false,
                      "capInsetsHeight": 0,
                      "capInsetsWidth": 0,
                      "capInsetsX": 0,
                      "capInsetsY": 0,
                      "clipAble": false,
                      "colorType": 0,
                      "direction": 2,
                      "gravity": 5,
                      "innerHeight": 82,
                      "innerWidth": 397,
                      "itemMargin": 1,
                      "vectorX": 0,
                      "vectorY": -0.5
                    }
                  }
                ],
                "options": {
                  "__type": "ComGUIPanelSurrogate:#EditorCommon.JsonModel.Component.GUI",
                  "classname": "Panel",
                  "name": "item_panel",
                  "ZOrder": 0,
                  "actiontag": 40796,
                  "anchorPointX": 0,
                  "anchorPointY": 0,
                  "classType": null,
                  "colorB": 255,
                  "colorG": 255,
                  "colorR": 255,
                  "flipX": false,
                  "flipY": false,
                  "height": 156,
                  "ignoreSize": false,
                  "layoutParameter": null,
                  "opacity": 255,
                  "positionPercentX": 0,
                  "positionPercentY": 0.6119403,
                  "positionType": 0,
                  "rotation": 0,
                  "scaleX": 1,
                  "scaleY": 1,
                  "sizePercentX": 1,
                  "sizePercentY": 0.3880597,
                  "sizeType": 0,
                  "tag": 907,
                  "touchAble": true,
                  "useMergedTexture": false,
                  "visible": true,
                  "width": 420,
                  "x": 0,
                  "y": 246,
                  "backGroundImage": null,
                  "backGroundImageData": null,
                  "backGroundScale9Enable": false,
                  "bgColorB": 255,
                  "bgColorG": 200,
                  "bgColorOpacity": 0,
                  "bgColorR": 150,
                  "bgEndColorB": 255,
                  "bgEndColorG": 200,
                  "bgEndColorR": 150,
                  "bgStartColorB": 255,
                  "bgStartColorG": 255,
                  "bgStartColorR": 255,
                  "capInsetsHeight": 0,
                  "capInsetsWidth": 0,
                  "capInsetsX": 0,
                  "capInsetsY": 0,
                  "clipAble": false,
                  "colorType": 0,
                  "layoutType": 0,
                  "vectorX": 0,
                  "vectorY": -0.5
                }
              },
              {
                "classname": "ImageView",
                "name": null,
                "children": [
                  {
                    "classname": "ImageView",
                    "name": null,
                    "children": [],
                    "options": {
                      "__type": "ComGUIImageViewSurrogate:#EditorCommon.JsonModel.Component.GUI",
                      "classname": "ImageView",
                      "name": "sweep",
                      "ZOrder": 1,
                      "actiontag": 40806,
                      "anchorPointX": 0.5,
                      "anchorPointY": 0.5,
                      "classType": null,
                      "colorB": 255,
                      "colorG": 255,
                      "colorR": 255,
                      "flipX": false,
                      "flipY": false,
                      "height": 53,
                      "ignoreSize": true,
                      "layoutParameter": null,
                      "opacity": 255,
                      "positionPercentX": 0,
                      "positionPercentY": 0.04888889,
                      "positionType": 0,
                      "rotation": 0,
                      "scaleX": 1,
                      "scaleY": 1,
                      "sizePercentX": 0.165631473,
                      "sizePercentY": 0.355555564,
                      "sizeType": 0,
                      "tag": 939,
                      "touchAble": false,
                      "useMergedTexture": false,
                      "visible": true,
                      "width": 200,
                      "x": 0,
                      "y": 11,
                      "capInsetsHeight": 0,
                      "capInsetsWidth": 0,
                      "capInsetsX": 0,
                      "capInsetsY": 0,
                      "fileName": null,
                      "fileNameData": {
                        "path": "typeface/sweep.png",
                        "plistFile": null,
                        "resourceType": 0
                      },
                      "scale9Enable": false,
                      "scale9Height": 53,
                      "scale9Width": 200
                    }
                  }
                ],
                "options": {
                  "__type": "ComGUIImageViewSurrogate:#EditorCommon.JsonModel.Component.GUI",
                  "classname": "ImageView",
                  "name": "effect",
                  "ZOrder": 1,
                  "actiontag": 40805,
                  "anchorPointX": 0.5,
                  "anchorPointY": 0.5,
                  "classType": null,
                  "colorB": 255,
                  "colorG": 255,
                  "colorR": 255,
                  "flipX": false,
                  "flipY": false,
                  "height": 225,
                  "ignoreSize": true,
                  "layoutParameter": null,
                  "opacity": 255,
                  "positionPercentX": 0.5,
                  "positionPercentY": 0.329602,
                  "positionType": 0,
                  "rotation": 0,
                  "scaleX": 1,
                  "scaleY": 1,
                  "sizePercentX": 0.1904762,
                  "sizePercentY": 0.199004978,
                  "sizeType": 0,
                  "tag": 938,
                  "touchAble": false,
                  "useMergedTexture": false,
                  "visible": true,
                  "width": 483,
                  "x": 210,
                  "y": 132,
                  "capInsetsHeight": 0,
                  "capInsetsWidth": 0,
                  "capInsetsX": 0,
                  "capInsetsY": 0,
                  "fileName": null,
                  "fileNameData": {
                    "path": "checkpoint/level_introduction/sweep/floor_2.png",
                    "plistFile": null,
                    "resourceType": 0
                  },
                  "scale9Enable": false,
                  "scale9Height": 225,
                  "scale9Width": 483
                }
              }
            ],
            "options": {
              "__type": "ComGUIListViewSurrogate:#EditorCommon.JsonModel.Component.GUI",
              "classname": "ListView",
              "name": "list_view",
              "ZOrder": 0,
              "actiontag": 40795,
              "anchorPointX": 0,
              "anchorPointY": 0,
              "classType": null,
              "colorB": 255,
              "colorG": 255,
              "colorR": 255,
              "flipX": false,
              "flipY": false,
              "height": 402,
              "ignoreSize": false,
              "layoutParameter": null,
              "opacity": 255,
              "positionPercentX": -0.427698582,
              "positionPercentY": -0.434343427,
              "positionType": 0,
              "rotation": 0,
              "scaleX": 1,
              "scaleY": 1,
              "sizePercentX": 0.855397165,
              "sizePercentY": 0.8121212,
              "sizeType": 0,
              "tag": 906,
              "touchAble": true,
              "useMergedTexture": false,
              "visible": true,
              "width": 420,
              "x": -210,
              "y": -215,
              "backGroundImage": null,
              "backGroundImageData": null,
              "backGroundScale9Enable": false,
              "bgColorB": 255,
              "bgColorG": 150,
              "bgColorOpacity": 0,
              "bgColorR": 150,
              "bgEndColorB": 255,
              "bgEndColorG": 150,
              "bgEndColorR": 150,
              "bgStartColorB": 255,
              "bgStartColorG": 255,
              "bgStartColorR": 255,
              "bounceEnable": false,
              "capInsetsHeight": 0,
              "capInsetsWidth": 0,
              "capInsetsX": 0,
              "capInsetsY": 0,
              "clipAble": true,
              "colorType": 0,
              "direction": 1,
              "gravity": 2,
              "innerHeight": 402,
              "innerWidth": 420,
              "itemMargin": 1,
              "vectorX": 0,
              "vectorY": -0.5
            }
          }
        ],
        "options": {
          "__type": "ComGUIImageViewSurrogate:#EditorCommon.JsonModel.Component.GUI",
          "classname": "ImageView",
          "name": "floor",
          "ZOrder": 1,
          "actiontag": 40053,
          "anchorPointX": 0.5,
          "anchorPointY": 0.5,
          "classType": null,
          "colorB": 255,
          "colorG": 255,
          "colorR": 255,
          "flipX": false,
          "flipY": false,
          "height": 495,
          "ignoreSize": true,
          "layoutParameter": null,
          "opacity": 255,
          "positionPercentX": 0.5,
          "positionPercentY": 0.5,
          "positionType": 1,
          "rotation": 0,
          "scaleX": 1,
          "scaleY": 1,
          "sizePercentX": 0.0711743757,
          "sizePercentY": 0.106666669,
          "sizeType": 0,
          "tag": 924,
          "touchAble": false,
          "useMergedTexture": false,
          "visible": true,
          "width": 491,
          "x": 562,
          "y": 375,
          "capInsetsHeight": 0,
          "capInsetsWidth": 0,
          "capInsetsX": 0,
          "capInsetsY": 0,
          "fileName": null,
          "fileNameData": {
            "path": "checkpoint/level_introduction/sweep/floor.png",
            "plistFile": null,
            "resourceType": 0
          },
          "scale9Enable": false,
          "scale9Height": 495,
          "scale9Width": 491
        }
      }
    ],
    "options": {
      "__type": "ComGUIPanelSurrogate:#EditorCommon.JsonModel.Component.GUI",
      "classname": "Panel",
      "name": "panel",
      "ZOrder": 0,
      "actiontag": -1,
      "anchorPointX": 0,
      "anchorPointY": 0,
      "classType": null,
      "colorB": 255,
      "colorG": 255,
      "colorR": 255,
      "flipX": false,
      "flipY": false,
      "height": 750,
      "ignoreSize": false,
      "layoutParameter": null,
      "opacity": 255,
      "positionPercentX": 0,
      "positionPercentY": 0,
      "positionType": 0,
      "rotation": 0,
      "scaleX": 1,
      "scaleY": 1,
      "sizePercentX": 1,
      "sizePercentY": 1,
      "sizeType": 0,
      "tag": 923,
      "touchAble": true,
      "useMergedTexture": false,
      "visible": true,
      "width": 1124,
      "x": 0,
      "y": 0,
      "backGroundImage": null,
      "backGroundImageData": null,
      "backGroundScale9Enable": false,
      "bgColorB": 0,
      "bgColorG": 0,
      "bgColorOpacity": 150,
      "bgColorR": 0,
      "bgEndColorB": 255,
      "bgEndColorG": 200,
      "bgEndColorR": 150,
      "bgStartColorB": 255,
      "bgStartColorG": 255,
      "bgStartColorR": 255,
      "capInsetsHeight": 0,
      "capInsetsWidth": 0,
      "capInsetsX": 0,
      "capInsetsY": 0,
      "clipAble": false,
      "colorType": 1,
      "layoutType": 0,
      "vectorX": 0,
      "vectorY": -0.5
    }
  }
}